pylint_relative_imports/__init__.py
pylint_relative_imports/relative_imports_checker.py
pylint_relative_imports/utils.py
pylint_relative_imports-0.0.4.dist-info/LICENSE
pylint_relative_imports-0.0.4.dist-info/METADATA
pylint_relative_imports-0.0.4.dist-info/WHEEL
pylint_relative_imports-0.0.4.dist-info/top_level.txt
pylint_relative_imports-0.0.4.dist-info/RECORD
